{
	"name": "02 Create Ratings",
	"properties": {
		"activities": [
			{
				"name": "Update Batch",
				"type": "SqlServerStoredProcedure",
				"dependsOn": [],
				"policy": {
					"timeout": "7.00:00:00",
					"retry": 0,
					"retryIntervalInSeconds": 30,
					"secureOutput": false,
					"secureInput": false
				},
				"userProperties": [],
				"typeProperties": {
					"storedProcedureName": "[dbo].[usp_LogBatchDetails]",
					"storedProcedureParameters": {
						"batch_id": {
							"value": {
								"value": "@pipeline().parameters.pbatch_id",
								"type": "Expression"
							},
							"type": "Int32"
						},
						"process_name": {
							"value": {
								"value": "@pipeline().Pipeline",
								"type": "Expression"
							},
							"type": "String"
						},
						"stage": {
							"value": "In Progress",
							"type": "String"
						}
					}
				},
				"linkedServiceName": {
					"referenceName": "NABERSStaging",
					"type": "LinkedServiceReference"
				}
			},
			{
				"name": "createRating",
				"type": "Copy",
				"dependsOn": [
					{
						"activity": "Update Batch",
						"dependencyConditions": [
							"Succeeded"
						]
					}
				],
				"policy": {
					"timeout": "7.00:00:00",
					"retry": 0,
					"retryIntervalInSeconds": 30,
					"secureOutput": false,
					"secureInput": false
				},
				"userProperties": [],
				"typeProperties": {
					"source": {
						"type": "AzureSqlSource",
						"sqlReaderStoredProcedureName": "[dbo].[usp_GetTransformedRatings]",
						"storedProcedureParameters": {
							"batchid": {
								"type": "Int32",
								"value": {
									"value": "@pipeline().parameters.pbatch_id",
									"type": "Expression"
								}
							}
						},
						"queryTimeout": "02:00:00"
					},
					"sink": {
						"type": "SalesforceSink",
						"writeBatchSize": 5000,
						"writeBehavior": "insert",
						"ignoreNullValues": false
					},
					"enableStaging": false,
					"translator": {
						"type": "TabularTranslator",
						"mappings": [
							{
								"source": {
									"name": "building_type",
									"type": "String"
								},
								"sink": {
									"name": "Building_Type__c",
									"type": "String"
								}
							},
							{
								"source": {
									"name": "source_rating_id"
								},
								"sink": {
									"name": "NO_Member_Rating_Id__c"
								}
							},
							{
								"source": {
									"name": ""
								}
							}
						]
					}
				},
				"inputs": [
					{
						"referenceName": "db_transformed_ratings",
						"type": "DatasetReference"
					}
				],
				"outputs": [
					{
						"referenceName": "sf_Ratings",
						"type": "DatasetReference"
					}
				]
			}
		],
		"parameters": {
			"pbatch_id": {
				"type": "int",
				"defaultValue": 1
			}
		},
		"annotations": []
	}
}